{
  "timestamp": "2026-05-18T18:27:04.990Z",
  "marks": [
    {
      "name": "sz:tabStore:start",
      "startTime": 137.9
    },
    {
      "name": "sz:tabStore:end",
      "startTime": 163.6
    },
    {
      "name": "sz:reactMount",
      "startTime": 164
    },
    {
      "name": "sz:app:render",
      "startTime": 165
    },
    {
      "name": "sz:suspense:taskShell:mount",
      "startTime": 176
    },
    {
      "name": "sz:appearance:start",
      "startTime": 176.1
    },
    {
      "name": "sz:loadBoardData:start",
      "startTime": 176.4
    },
    {
      "name": "sz:app:mounted",
      "startTime": 176.7
    },
    {
      "name": "sz:telemetry:start",
      "startTime": 177.2
    },
    {
      "name": "sz:theme:start",
      "startTime": 177.2
    },
    {
      "name": "sz:pty:start",
      "startTime": 177.3
    },
    {
      "name": "sz:app:render",
      "startTime": 177.5
    },
    {
      "name": "sz:appearance:end",
      "startTime": 197.2
    },
    {
      "name": "sz:loadBoardData:end",
      "startTime": 197.5
    },
    {
      "name": "sz:dataReady",
      "startTime": 197.5
    },
    {
      "name": "sz:app:render",
      "startTime": 198.1
    },
    {
      "name": "sz:app:render",
      "startTime": 213.6
    },
    {
      "name": "sz:app:render",
      "startTime": 224.6
    },
    {
      "name": "sz:theme:end",
      "startTime": 225.6
    },
    {
      "name": "sz:pty:end",
      "startTime": 225.7
    },
    {
      "name": "sz:app:render",
      "startTime": 226.2
    },
    {
      "name": "sz:app:render",
      "startTime": 233.9
    },
    {
      "name": "sz:telemetry:end",
      "startTime": 254.2
    },
    {
      "name": "sz:app:render",
      "startTime": 265.8
    },
    {
      "name": "sz:suspense:taskShell:unmount",
      "startTime": 279.9
    }
  ],
  "phases": {
    "tabStore": {
      "startMs": 0,
      "endMs": 25.7,
      "durationMs": 25.7
    },
    "theme": {
      "startMs": 39.3,
      "endMs": 87.7,
      "durationMs": 48.4
    },
    "pty": {
      "startMs": 39.4,
      "endMs": 87.8,
      "durationMs": 48.4
    },
    "appearance": {
      "startMs": 38.2,
      "endMs": 59.3,
      "durationMs": 21.1
    },
    "telemetry": {
      "startMs": 39.3,
      "endMs": 116.3,
      "durationMs": 77
    },
    "loadBoardData": {
      "startMs": 38.5,
      "endMs": 59.6,
      "durationMs": 21.1
    }
  },
  "waterfall": [
    "Phase                    Start     Dur  Timeline",
    "────────────────────────────────────────────────────────────────────────────────────────────",
    "Tab Store                  0ms  25.7ms  |█████████",
    "React Mount             26.1ms          |         ▼",
    "Theme                   39.3ms  48.4ms  |              █████████████████",
    "PTY Seed                39.4ms  48.4ms  |              █████████████████",
    "Appearance              38.2ms  21.1ms  |             ████████",
    "Telemetry               39.3ms    77ms  |              ███████████████████████████",
    "Load Board              38.5ms  21.1ms  |              ███████",
    "Data Ready              59.6ms          |                     ▼",
    "Suspense #1             38.1ms 103.9ms  |             ░░░░░░░░░░░░░░░░░░░░░░░░░░░░░░░░░░░░░"
  ],
  "summary": {
    "tabStoreMs": 25.7,
    "reactMountAt": 26.1,
    "loadBoardDataMs": 21.1,
    "dataReadyAt": 59.6,
    "themeMs": 48.4,
    "ptyMs": 48.4,
    "appearanceMs": 21.1,
    "telemetryMs": 77,
    "appFirstRenderAt": 27.1,
    "appMountedAt": 38.8,
    "suspenseFallbackCount": 1,
    "suspenseFallbackDurations": [
      103.9
    ],
    "totalStartupMs": 59.6
  }
}